kfpxtend/__init__.py
kfpxtend/_auth.py
kfpxtend/_client.py
kfpxtend/_component_store.py
kfpxtend/_components.py
kfpxtend/_operators.py
kfpxtend/_pipeline.py
kfpxtend-1.1.2.dist-info/METADATA
kfpxtend-1.1.2.dist-info/WHEEL
kfpxtend-1.1.2.dist-info/top_level.txt
kfpxtend-1.1.2.dist-info/RECORD
