Metadata-Version: 2.1
Name: kfpxtend
Version: 1.1.2
Summary: High level of kubeflow SDK
Home-page: UNKNOWN
Author: Le Tuan Vu
Author-email: ltnv24@gmail.com
License: UNKNOWN
Platform: UNKNOWN
Classifier: Programming Language :: Python :: 3
Classifier: Operating System :: OS Independent
Requires-Python: >=3.6
Requires-Dist: kfp
